{
  "reference": "A8/A8frontendscipts/2.0.1 only (vendor/ui-bundle excluded)",
  "a8": {
    "jsBytes": 2905708,
    "cssBytes": 372862,
    "viewCount": 25,
    "views": [
      "AccountInfoView",
      "AccountView",
      "CreateLoseView",
      "ExtensionsView",
      "FollowView",
      "HomeView",
      "LimitDiagView",
      "LoginView",
      "LoseOrderView",
      "MoneyInfoView",
      "MoneyRiskView",
      "MoneyView",
      "OrderView",
      "TradeView",
      "UserChatMessageView",
      "UserCollectView",
      "UserConfigView",
      "UserDiagView",
      "UserInfoView",
      "UserMessageView",
      "UserPasswordView",
      "UserProxyView",
      "UserRankView",
      "UserReportView",
      "UserWalletView"
    ]
  },
  "changmen": {
    "a8CssBytes": 371511,
    "a8CssExtractedFrom": "scripts/extract-a8-css.mjs -> src/styles/a8.css"
  },
  "css": {
    "a8SelectorCount": 1816,
    "changmenA8CssSelectorCount": 1816,
    "selectorOnlyInA8Count": 0,
    "selectorOnlyInChangmenA8CssCount": 0,
    "selectorOnlyInA8": [],
    "selectorOnlyInChangmenA8Css": []
  },
  "clientApis": {
    "inA8": [
      "Client_CreateTagPlatform",
      "Client_DeleteMoneyLog",
      "Client_DeletePlayer",
      "Client_GetChatHistory",
      "Client_GetCollectPlatform",
      "Client_GetData",
      "Client_GetDefaultOdds",
      "Client_GetGames",
      "Client_GetMatchDefaultOdds",
      "Client_GetMatchs",
      "Client_GetMoneyLog",
      "Client_GetMoneyLogs",
      "Client_GetOrderList",
      "Client_GetPlayerOrder",
      "Client_GetTagPlatforms",
      "Client_GetUserDetail",
      "Client_GetUserInfo",
      "Client_GetUserProfit",
      "Client_GetUsers",
      "Client_Login",
      "Client_Logout",
      "Client_MonthReport",
      "Client_SaveData",
      "Client_SaveMoneyLog",
      "Client_SaveOrder",
      "Client_SaveOrderBind",
      "Client_SaveUserLog",
      "Client_UpdateBalance"
    ],
    "missingInChangmenSrc": []
  },
  "apiPaths": {
    "inA8NotInSrc": [
      "/api/game/user/getUserHistory/"
    ]
  },
  "unmappedA8Views": [],
  "viewMarkerGaps": [
    {
      "view": "AccountInfoView",
      "files": [
        "components/account/AccountEditDialog.vue"
      ],
      "missingMarkers": [
        "class:am-icon-info-circle",
        "class:box-item",
        "class:gap-10",
        "class:tags",
        "label:同名检测：",
        "label:城市检测：",
        "label:手机检测：",
        "title:单个盘口的最多下注单数",
        "title:当前场馆的自定义利润要求，如果匹配到当前场馆，可覆盖全局的最低利润要求。为0表示使用全局默认值"
      ]
    },
    {
      "view": "MoneyInfoView",
      "files": [
        "components/account/MoneyInfoDialog.vue"
      ],
      "missingMarkers": [
        "class:pageSplit",
        "class:report",
        "class:tip"
      ]
    },
    {
      "view": "MoneyView",
      "files": [
        "components/account/MoneyLogDialog.vue",
        "components/account/AccountCard.vue"
      ],
      "missingMarkers": [
        "class:providers"
      ]
    },
    {
      "view": "AccountView",
      "files": [
        "components/account/AccountBar.vue",
        "components/account/AccountCard.vue"
      ],
      "missingMarkers": [
        "class:submit"
      ]
    },
    {
      "view": "UserConfigView",
      "files": [
        "components/user/UserConfigDialog.vue"
      ],
      "missingMarkers": [
        "class:box-item",
        "class:code",
        "class:googlecode"
      ]
    },
    {
      "view": "UserReportView",
      "files": [
        "components/user/tabs/UserDiagReportTab.vue"
      ],
      "missingMarkers": [
        "class:name",
        "class:profit",
        "class:rank"
      ]
    },
    {
      "view": "UserCollectView",
      "files": [
        "components/user/tabs/UserDiagCollectTab.vue",
        "components/user/CollectConfigPanel.vue"
      ],
      "missingMarkers": [
        "class:OB",
        "class:PB",
        "class:SABA"
      ]
    },
    {
      "view": "FollowView",
      "files": [
        "components/user/tabs/UserDiagFollowTab.vue"
      ],
      "missingMarkers": [
        "class:log",
        "class:tags",
        "class:text-center",
        "class:top"
      ]
    },
    {
      "view": "UserChatMessageView",
      "files": [
        "components/user/tabs/UserDiagChatTab.vue"
      ],
      "missingMarkers": [
        "class:action",
        "class:address",
        "class:balance",
        "class:header",
        "class:name",
        "class:tit",
        "class:trx",
        "class:usdt",
        "class:wallet"
      ]
    },
    {
      "view": "UserInfoView",
      "files": [
        "components/user/UserInfoPanel.vue"
      ],
      "missingMarkers": [
        "class:date",
        "class:item",
        "class:player",
        "class:profit",
        "class:time"
      ]
    },
    {
      "view": "OrderView",
      "files": [
        "components/order/OrderView.vue",
        "components/order/LoseOrderView.vue"
      ],
      "missingMarkers": [
        "label:全部"
      ]
    },
    {
      "view": "ExtensionsView",
      "files": [
        "components/layout/ExtensionsBadge.vue"
      ],
      "missingMarkers": [
        "class:item"
      ]
    },
    {
      "view": "LimitDiagView",
      "files": [
        "components/match/LimitDiagDialog.vue",
        "components/match/BetRow.vue",
        "components/match/MatchCard.vue"
      ],
      "missingMarkers": [
        "class:common-layout",
        "class:matchs"
      ]
    },
    {
      "view": "HomeView",
      "files": [
        "views/HomeView.vue",
        "components/match/MatchCard.vue",
        "components/match/BetRow.vue",
        "components/layout/AppSidebar.vue"
      ],
      "missingMarkers": [
        "class:loginbox"
      ]
    }
  ],
  "literalGaps": [
    {
      "literal": "同名检测",
      "inA8": true,
      "inChangmenSrc": false
    },
    {
      "literal": "手机检测",
      "inA8": true,
      "inChangmenSrc": false
    },
    {
      "literal": "城市检测",
      "inA8": true,
      "inChangmenSrc": false
    },
    {
      "literal": "单个盘口",
      "inA8": true,
      "inChangmenSrc": false
    },
    {
      "literal": "getUserHistory",
      "inA8": true,
      "inChangmenSrc": false
    },
    {
      "literal": "loseorder-container",
      "inA8": true,
      "inChangmenSrc": true
    }
  ]
}